perovskite_solar_cell_database/__init__.py
perovskite_solar_cell_database/composition.py
perovskite_solar_cell_database/llm_extraction_schema.py
perovskite_solar_cell_database/schema.py
perovskite_solar_cell_database/synonym_map.json
perovskite_solar_cell_database/utils.py
perovskite_solar_cell_database/actions/__init__.py
perovskite_solar_cell_database/actions/llm_extractor/__init__.py
perovskite_solar_cell_database/actions/llm_extractor/activities.py
perovskite_solar_cell_database/actions/llm_extractor/models.py
perovskite_solar_cell_database/actions/llm_extractor/utils.py
perovskite_solar_cell_database/actions/llm_extractor/workflows.py
perovskite_solar_cell_database/apps/__init__.py
perovskite_solar_cell_database/apps/llm_extracted_solarcells.py
perovskite_solar_cell_database/apps/perovskite_ions_app.py
perovskite_solar_cell_database/apps/perovskite_solar_cell_database_app.py
perovskite_solar_cell_database/apps/perovskite_solar_cell_database_dashboard.yaml
perovskite_solar_cell_database/apps/solar_cell_app.py
perovskite_solar_cell_database/apps/tandem_app.py
perovskite_solar_cell_database/apps/tandem_dashboard.yaml
perovskite_solar_cell_database/data_tools/AM15G.dat.txt
perovskite_solar_cell_database/data_tools/README.md
perovskite_solar_cell_database/data_tools/__init__.py
perovskite_solar_cell_database/data_tools/entry_writer.py
perovskite_solar_cell_database/data_tools/eqe_parser.py
perovskite_solar_cell_database/data_tools/jv_parser.py
perovskite_solar_cell_database/example_uploads/__init__.py
perovskite_solar_cell_database/example_uploads/ions_database/C2NH7S.xyz
perovskite_solar_cell_database/example_uploads/ions_database/CNH6.xyz
perovskite_solar_cell_database/example_uploads/ions_database/build-perovskite-structure-from-ion-entry.ipynb
perovskite_solar_cell_database/example_uploads/ions_database/query-ion-database-api.ipynb
perovskite_solar_cell_database/example_uploads/ions_database/query-perovskite-composition.ipynb
perovskite_solar_cell_database-1.2.12.dist-info/licenses/LICENSE
perovskite_solar_cell_database-1.2.12.dist-info/METADATA
perovskite_solar_cell_database-1.2.12.dist-info/WHEEL
perovskite_solar_cell_database-1.2.12.dist-info/entry_points.txt
perovskite_solar_cell_database-1.2.12.dist-info/top_level.txt
perovskite_solar_cell_database-1.2.12.dist-info/RECORD
