Metadata-Version: 2.4
Name: perovskite-solar-cell-database
Version: 1.2.12
Summary: Perovskite solar cell data schema plugin for NOMAD.
Author-email: Jose Marquez <jose.marquez@physik.hu-berlin.de>, Yaru Wang <wangyaru@physik.hu-berlin.de>, Hampus Näsström <hampus.naesstroem@physik.hu-berlin.de>, Lev Ginzburg <ginzburl@physik.hu-berlin.de>, Sherjeel Shabih <sshabih@physik.hu-berlin.de>
Maintainer-email: Jose Marquez <jose.marquez@physik.hu-berlin.de>, Hampus Näsström <hampus.naesstroem@physik.hu-berlin.de>
License:                                  Apache License
Project-URL: Homepage, https://github.com/FAIRmat-NFDI/nomad-perovskite-solar-cells-database
Project-URL: Repository, https://github.com/FAIRmat-NFDI/nomad-perovskite-solar-cells-database
Classifier: Intended Audience :: Developers
Classifier: Operating System :: OS Independent
Classifier: Programming Language :: Python
Classifier: Programming Language :: Python :: 3.10
Classifier: Programming Language :: Python :: 3.11
Classifier: Programming Language :: Python :: 3.12
Classifier: License :: OSI Approved :: Apache Software License
Requires-Python: >=3.10
License-File: LICENSE
Requires-Dist: nomad-lab>=1.4.0
Requires-Dist: nomad-schema-plugin-run>=1.0.1
Requires-Dist: nomad-schema-plugin-simulation-workflow>=1.0.1
Requires-Dist: rdkit
Requires-Dist: openpyxl
Requires-Dist: lxml_html_clean
Requires-Dist: pyarrow>=22.0.0
Requires-Dist: nbformat>=5.10.4
Provides-Extra: dev
Requires-Dist: pytest; extra == "dev"
Requires-Dist: ruff; extra == "dev"
Requires-Dist: structlog; extra == "dev"
Requires-Dist: python-logstash; extra == "dev"
Requires-Dist: mkdocs; extra == "dev"
Requires-Dist: mkdocs-material>=9.0; extra == "dev"
Requires-Dist: pymdown-extensions; extra == "dev"
Requires-Dist: mkdocs-click; extra == "dev"
Requires-Dist: mkdocs-macros-plugin>=1.0; extra == "dev"
Requires-Dist: mkdocs-jupyter; extra == "dev"
Requires-Dist: mkdocs-glightbox; extra == "dev"
Requires-Dist: pydantic>=2.0; extra == "dev"
Requires-Dist: nomad-docs>=0.1.3; extra == "dev"
Provides-Extra: extraction
Requires-Dist: perla-extract>=0.0.4; extra == "extraction"
Provides-Extra: notebooks
Requires-Dist: huggingface_hub>=0.20; extra == "notebooks"
Requires-Dist: nbformat; extra == "notebooks"
Requires-Dist: dabest; extra == "notebooks"
Dynamic: license-file
